src/__init__.py
src/base_models.py
src/factory.py
src/http_response_models.py
cbaxter1988_models-0.0.1.dist-info/METADATA
cbaxter1988_models-0.0.1.dist-info/WHEEL
cbaxter1988_models-0.0.1.dist-info/top_level.txt
cbaxter1988_models-0.0.1.dist-info/RECORD
