Metadata-Version: 2.1
Name: cbaxter1988-models
Version: 0.0.1
Summary: Collection of common models
Home-page: http://www.github.com/cbaxter1988
Author: Courtney S Baxter Jr
Author-email: cbaxtertech@gmail.com
License: UNKNOWN
Platform: UNKNOWN
